siphash24.cpython-38-darwin.so
siphash24-1.5.dist-info/RECORD
siphash24-1.5.dist-info/WHEEL
siphash24-1.5.dist-info/METADATA
