Metadata-Version: 2.1
Name: siphash24
Version: 1.5
Summary: Streaming-capable SipHash-1-3 and SipHash-2-4 Implementation
Maintainer-Email: Daniele Nicolodi <daniele@grinta.net>
Classifier: Development Status :: 5 - Production/Stable
Classifier: License :: OSI Approved :: Apache Software License
Classifier: License :: OSI Approved :: GNU Lesser General Public License v2 or later (LGPLv2+)
Classifier: Programming Language :: C
Classifier: Programming Language :: Python
Classifier: Programming Language :: Python :: 3
Classifier: Programming Language :: Python :: 3.7
Classifier: Programming Language :: Python :: 3.8
Classifier: Programming Language :: Python :: 3.9
Classifier: Programming Language :: Python :: 3.10
Classifier: Programming Language :: Python :: 3.11
Classifier: Programming Language :: Python :: 3.12
Classifier: Topic :: Software Development :: Libraries
Project-URL: Documentation, https://dnicolodi.github.io/python-siphash24/
Project-URL: Source, https://github.com/dnicolodi/python-siphash24/
Project-URL: Issue tracker, https://github.com/dnicolodi/python-siphash24/issues
Requires-Python: >=3.7
